tkl.py
tkl-0.9.0.dist-info/LICENSE
tkl-0.9.0.dist-info/WHEEL
tkl-0.9.0.dist-info/METADATA
tkl-0.9.0.dist-info/RECORD
